shapmonitor/__init__.py
shapmonitor/analysis/__init__.py
shapmonitor/analysis/_analyzer.py
shapmonitor/analysis/metrics.py
shapmonitor/backends/__init__.py
shapmonitor/backends/_base.py
shapmonitor/backends/_parquet.py
shapmonitor/exceptions.py
shapmonitor/integrations/__init__.py
shapmonitor/monitor.py
shapmonitor/types.py
shap_monitor-0.0.7.dist-info/METADATA
shap_monitor-0.0.7.dist-info/WHEEL
shap_monitor-0.0.7.dist-info/licenses/LICENSE
shap_monitor-0.0.7.dist-info/RECORD
