Metadata-Version: 2.4
Name: shap-monitor
Version: 0.0.7
Summary: A monitoring tool for SHAP values in machine learning models.
License: Apache-2.0
License-File: LICENSE
Keywords: shap,monitoring,machine-learning,explainability,data-science
Author: Avik Basu
Maintainer: Avik Basu
Requires-Python: >=3.11
Classifier: Development Status :: 2 - Pre-Alpha
Classifier: Intended Audience :: Developers
Classifier: Intended Audience :: Science/Research
Classifier: Operating System :: OS Independent
Classifier: License :: OSI Approved :: Apache Software License
Classifier: Programming Language :: Python :: 3 :: Only
Classifier: Programming Language :: Python :: 3.11
Classifier: Programming Language :: Python :: 3.12
Classifier: Programming Language :: Python :: 3.13
Classifier: Programming Language :: Python :: 3.14
Classifier: Topic :: Software Development :: Libraries
Classifier: Topic :: Scientific/Engineering :: Artificial Intelligence
Classifier: Topic :: Scientific/Engineering :: Information Analysis
Requires-Dist: numpy (>=1.26.0,<3.0.0)
Requires-Dist: pandas (>=2.0.0,<3.0.0)
Requires-Dist: pyarrow (>=17.0.0,<23.0.0)
Requires-Dist: shap (>=0.45.0,<0.51.0)
Project-URL: Documentation, https://ab93.github.io/shap-monitor/
Project-URL: Homepage, https://github.com/ab93/shap-monitor
Project-URL: Issues, https://github.com/ab93/shap-monitor/issues
Project-URL: Source, https://github.com/ab93/shap-monitor
